imreco/__init__.py
imreco/compressor.py
imreco/converter.py
imreco/imreco.py
imreco/resizer.py
imreco-1.0.1.dist-info/LICENSE
imreco-1.0.1.dist-info/METADATA
imreco-1.0.1.dist-info/WHEEL
imreco-1.0.1.dist-info/entry_points.txt
imreco-1.0.1.dist-info/RECORD
