Metadata-Version: 2.1
Name: imreco
Version: 1.0.1
Summary: A cli program to resize images and convert between different formats.
License: MIT
Keywords: image,resizer,converter,compresser
Author: Tamton Aquib
Author-email: aquibjavedt007@gmail.com
Requires-Python: >=3.11,<4.0
Classifier: License :: OSI Approved :: MIT License
Classifier: Programming Language :: Python :: 3
Classifier: Programming Language :: Python :: 3.11
Classifier: Programming Language :: Python :: 3.12
Requires-Dist: flake8 (>=7.0.0,<8.0.0)
Requires-Dist: opencv-python (>=4.9.0.80,<5.0.0.0)
Requires-Dist: pytest (>=8.0.2,<9.0.0)
